moddingtextparser/__init__.py
moddingtextparser/main.py
moddingtextparser/prompts.py
moddingtextparser-2025.12.21151340.dist-info/METADATA
moddingtextparser-2025.12.21151340.dist-info/WHEEL
moddingtextparser-2025.12.21151340.dist-info/top_level.txt
moddingtextparser-2025.12.21151340.dist-info/RECORD
