Metadata-Version: 2.4
Name: moddingtextparser
Version: 2025.12.21151340
Summary: A new package is designed to analyze user-provided text questions about technical modding topics to identify key concepts, such as detecting mentions of premium checks within Android app modifications
Author-email: moddingtextparser <hi@eugene.plus>
License: MIT
Project-URL: Homepage, https://github.com/chigwell/moddingtextparser
Requires-Python: >=3.9
Requires-Dist: langchain-llm7>=0.0.0
Requires-Dist: llmatch-messages>=0.0.0
Requires-Dist: langchain-core>=0.3.0
